README.rst
setup.cfg
setup.py
overlock/__init__.py
overlock/errors.py
overlock/install.py
overlock/state.py
overlock/util.py
overlock.egg-info/PKG-INFO
overlock.egg-info/SOURCES.txt
overlock.egg-info/dependency_links.txt
overlock.egg-info/requires.txt
overlock.egg-info/top_level.txt
overlock/client/__init__.py
overlock/client/base.py
overlock/client/http.py
overlock/client/worker.py
overlock/logger/__init__.py
overlock/logger/base.py
overlock/logger/impl.py