Metadata-Version: 1.1
Name: overlock
Version: 0.3.0
Summary: Overlock client library for instrumenting code
Home-page: https://github.com/overlockIoT/python
Author: Michael Boulton
Author-email: michael@overlock.io
License: UNKNOWN
Download-URL: https://github.com/overlockIoT/python
Keywords: iot,overlock
Platform: UNKNOWN
